{
  "-redacted-": 1296,
  "/wall": 1466,
  "1 Billion": 26396,
  "10 Billion": 7067,
  "4x99 guide by jackie": 2817,
  "A Special Request From Buddy": 6526,
  "A Towering Investment": 26088,
  "A Way Back": 15669,
  "Accidental Beets": 746,
  "Achievements": 3771,
  "Acorn Alliance": 1309,
  "Alpha Testing": 23335,
  "Ancient Coins": 2810,
  "Apple Cider": 3880,
  "Arnie Palmies": 500,
  "Arnold Palmer": 2130,
  "Art gallery": 509,
  "Artifacts": 3261,
  "Ascension Knowledge": 11005,
  "Autocrafting": 1519,
  "Awoir": 144,
  "Bacon": 6696,
  "Baits": 5586,
  "Bank Interest": 2848,
  "Battleship": 209,
  "Because Ffff refuses to Discord": 173,
  "Beef Tips": 13051,
  "Best FarmRPG player": 3494,
  "Beta Testing": 86358,
  "Bhelogans videos for farmers who can\u2019t read good": 473,
  "Big Onion": 184,
  "Blue Dragon": 1023,
  "Books": 2607,
  "Borgen Shop": 6340,
  "Brown Bear": 1563,
  "Buddy": 13726,
  "Buddy Snowballs": 378,
  "Buddy gang": 2075,
  "Buddy's Snowballs": 3301,
  "Building Upgrades": 58761,
  "CC Bug": 2969,
  "Camp MB": 1040,
  "Capybara Gang": 945,
  "Charles Horsington III": 504,
  "Chat Commands": 27718,
  "Chat Guide": 213,
  "Cheats": 16967,
  "Chicken Coop": 6182,
  "Chimera": 519,
  "Choicy Trivia": 315,
  "Cid's Stone Ale": 358,
  "Cid\u2019s stone ale": 208,
  "Click Here": 201,
  "Click This Link": 6887,
  "Cobalt Tarantula": 674,
  "Code of Misconduct": 89,
  "Code of conduct": 1260,
  "Coffee": 1184,
  "Common Issues": 3971,
  "Community Center": 5170,
  "Community Guides": 50300,
  "Country Store": 1447,
  "Cow Pasture": 9801,
  "Cowboy Hat Gang": 707,
  "Crafting": 41391,
  "Cthulhu\u2019s Gang": 968,
  "Daily Chores": 4598,
  "Dark Library": 1454,
  "Dark Mode": 5963,
  "Did Not Read The Quest": 15108,
  "Discord": 406,
  "Drop Pain Chart": 643,
  "EGGRPG Trivia": 2071,
  "ENT": 1247,
  "Echo": 800,
  "Eggplant Winter": 2887,
  "Emperor Penguin": 589,
  "Event Item List": 4485,
  "Exploring": 58402,
  "Exploring Drops": 47794,
  "FAQ": 170603,
  "FRPG lingo": 5994,
  "Faith in Humanity": 3560,
  "Farm Pond": 5605,
  "Farm Supply": 821,
  "FarmGate": 148,
  "FarmRPG Cheats": 1421,
  "FarmRPG Staff": 7069,
  "Farmhouse": 6763,
  "Farming": 55777,
  "Farming Skill": 2080,
  "Feed Mill": 14296,
  "Ffff": 675,
  "Ffff2": 322,
  "Find A Way": 4034,
  "Find It": 78932,
  "Fine Fishing": 6746,
  "Firefly-class Multipurpose, Mid-Bulk Transport ship gang": 1621,
  "Firestream": 1515,
  "Fishing": 46444,
  "Fishing Drops Zone": 9023,
  "Fishing Rates": 7105,
  "Fishing Streak": 878,
  "Fishing Streaks": 13437,
  "Flamingo Gang": 1047,
  "Flea Market": 403,
  "Flour Mill": 8139,
  "Flour Mill vs Feed Mill": 1532,
  "Foe": 7031,
  "Forbidden Corn": 662,
  "Forbidden Talk": 1131,
  "Forest": 8861,
  "Forever": 553,
  "GET ITEM": 474,
  "Game Suggestions": 995,
  "Garnet": 1327,
  "Get Rich Quick": 56632,
  "Giveaways Guide": 148,
  "Gold": 4076,
  "Gold Currency": 15241,
  "Gold crops": 4783,
  "Golden Crops": 284,
  "Good Night": 816,
  "Goodies": 2839,
  "Gorilla Gang": 212,
  "Grape Juice": 4092,
  "Gray Hedgehog": 1114,
  "Greater Capybara": 1749,
  "Green Dragon": 628,
  "Green Python": 991,
  "Green Tractor Society Gang": 711,
  "Gullible": 426,
  "Halloween FAQ": 1169,
  "Hands": 539,
  "Happy Worm Oprah Day": 259,
  "Hay Field": 3495,
  "Help Requests": 3976,
  "Hide Craftable Items": 497,
  "Home": 1519723,
  "Hot Potat": 676,
  "Hot Potato": 1313,
  "I Like The Game": 1261,
  "IOTD": 4815,
  "Iced Tea": 2597,
  "Infinite Gold": 14851,
  "Inventory Growth": 3405,
  "Inventory Monitor": 1357,
  "Iron Cup": 183,
  "Iron Depot": 1272,
  "Ironworks": 5962,
  "Item List": 36680,
  "Item Mastery": 18729,
  "Item Mastery List": 2329,
  "KiaKatt": 180,
  "Large Nets": 1316,
  "Leaf Gang": 935,
  "Leek Spin": 829,
  "Lemonade": 3717,
  "Library": 273,
  "Library Updates": 7696,
  "Locksmith": 137624,
  "MB": 506,
  "Mailbox Passwords": 190921,
  "Making page names based on what KiaKatt can remember": 304,
  "Mandrill Baboon": 825,
  "Married": 838,
  "Mastery Guide by Null": 11902,
  "Mastery Tracker": 380,
  "Mayor Trid": 419,
  "Mealworms": 1257,
  "Meme Contest": 2938,
  "Merit Badges": 1372,
  "Milkbark": 1518,
  "Missing Required Item": 1469,
  "Museum": 749,
  "Museum Completion": 10599,
  "NA7E": 35,
  "Net Worth": 16603,
  "Nicholas Cage": 236,
  "Ninja Gang": 335,
  "No, for real, who's really the best FarmRPG player?": 937,
  "NoVelcroShoes": 160,
  "Not Updates": 473,
  "Off My Lawn gang": 2080,
  "Onion Cutie": 938,
  "Onion Foe": 767,
  "Onion Friend": 286,
  "Orange Juice": 3231,
  "Orchard": 11101,
  "Overview": 67443,
  "PTLBB": 1896,
  "PTLBa": 5742,
  "Page Not Found": 141,
  "Pass": 532,
  "Passwords": 4860,
  "Patreon Support": 2341,
  "Peac?h Cobbler": 121,
  "Pepperidge Farms": 615,
  "Perk Points": 1620,
  "Perk Sets": 3637,
  "Perk Tier List by Bhelogan": 51969,
  "Perks": 13781,
  "Pet Rock": 748,
  "Pet Shop": 52486,
  "Pets": 9954,
  "Pig Pen": 11479,
  "Podcast": 5806,
  "Poseidon": 806,
  "Pretty Pink Cupcake Gang": 287,
  "Punny Pet Gang": 1322,
  "Quarry": 10572,
  "R.O.U.S.": 2442,
  "Random Jokes": 394,
  "Random Words": 646,
  "Raptor Gang": 1593,
  "Raptor Pen": 17693,
  "Read the quest": 23466,
  "Red Dragon": 734,
  "Red Squirrel": 1053,
  "Referral System": 15292,
  "Renthisj": 661,
  "Rescue Animals": 686,
  "Reset Bug": 4370,
  "Ring-Tailed Lemur": 988,
  "Roman": 766,
  "Rudolph": 284,
  "Rune Stones": 4428,
  "Runesrones": 4268,
  "Runestones": 286547,
  "Santas workshop": 880,
  "Saph\u2019s Giveaways Advice": 414,
  "Saturn Gang": 879,
  "Sawmill": 11456,
  "Sawmill silver": 55246,
  "Sealworm": 45,
  "Secrets": 864,
  "Server Time": 17,
  "Shark Fin Gang": 239,
  "Siberian Husky": 899,
  "Silver": 498,
  "Slaughterhouse": 20999,
  "Small Cave": 10542,
  "Special Drinks": 16959,
  "Ssss": 17,
  "Stamina Effectiveness": 15271,
  "Steak": 247,
  "Storehouse": 7497,
  "Strange Companions": 5258,
  "Strange Onion": 1110,
  "Sunflowers": 900,
  "Supporter": 573,
  "Tawny Owl": 987,
  "Tenfoo": 179,
  "Testimonials": 4043,
  "The Egg": 3477,
  "The Game": 427,
  "The Tower": 6311,
  "The Tower (update)": 1365,
  "The Void": 4560,
  "There\u2019s A Way": 8606,
  "Titan Conquest": 893,
  "Tower": 14541,
  "Tower Links": 1599,
  "Town": 63753,
  "Townsfolk": 28131,
  "Townsfolk 2": 972,
  "Trade Guide": 26514,
  "Tree Frog": 809,
  "Trident of Poseidon": 1069,
  "Trivia": 767,
  "Trivia Games": 358,
  "Trout / Bait Farm": 374,
  "Trout Farm": 6435,
  "Valentine's Day Event": 378,
  "Video Tutorials": 8253,
  "Videos": 37,
  "Vineyard": 9785,
  "Virtual Night Trivia": 1150,
  "WTFAQ": 837,
  "WW": 1288,
  "WXF Spoilers": 35225,
  "Welcome": 130,
  "Whale Gang": 2586,
  "What Just Happened": 97,
  "Wheel Grease": 610,
  "When Jessica updates a library page": 176,
  "Wild Boar": 613,
  "Wine": 2556,
  "Wine Cellar": 25578,
  "Wine-o-Matic": 677,
  "Wishing Well": 78088,
  "Workshop": 4901,
  "Workshop Favorites": 371,
  "World Map": 1668,
  "Worm Habitat": 4418,
  "Zoom Bug": 606,
  "[Ffff]": 396,
  "[GET ITEM]": 145,
  "[[Ffff]]": 31,
  "a barren wasteland": 7536,
  "a place": 484,
  "apple gang": 339,
  "auggie": 471,
  "auggiesnack": 950,
  "back the faq up": 238,
  "banded armadillo": 602,
  "bandit armadillo": 418,
  "bat gang": 1862,
  "bc": 1929,
  "best upgrades": 29234,
  "beta tester": 191,
  "bhelogan": 187,
  "bobs gang": 1168,
  "bonk": 4835,
  "buddy farm": 460,
  "buddy understands and buddy cares": 332,
  "buddy.farm": 764,
  "buddyfarm": 57,
  "building upgrade": 224,
  "bye": 327,
  "caps": 3201,
  "capybara": 1856,
  "cat gang": 337,
  "chicken nuggets": 469,
  "choice hurl": 137,
  "choice veil": 145,
  "clover gang": 504,
  "conspiracies": 186,
  "cooked turkey": 741,
  "corn gang": 2448,
  "corn jail": 4763,
  "crab Claws": 809,
  "crafting advice": 39146,
  "crafting guide": 563,
  "daily reset": 5012,
  "do the CC": 776,
  "doggo": 576,
  "don't sell": 4,
  "don't sell it": 830,
  "dont sell it": 28576,
  "dont sell it again": 18,
  "don\u2019t sell it": 760,
  "exploring effectiveness": 888,
  "farmer ranks": 567,
  "farmrpg podcast": 26,
  "finnLEE": 66,
  "firesnack": 1548,
  "firestream adding stuff to his list": 150,
  "first billion": 1606,
  "fish bones": 458,
  "fish bot": 141,
  "frank": 507,
  "free": 5074,
  "frong": 1701,
  "gangs": 15621,
  "gas mask gang": 845,
  "gg": 105,
  "ghost gang": 980,
  "globber gang": 794,
  "gnome gang": 718,
  "gold coral": 747,
  "gold corral": 302,
  "gold egg plant gang": 69,
  "goose gang": 1350,
  "grapes": 1124,
  "guides": 234,
  "hayfield": 231,
  "help": 2756,
  "hi": 72,
  "hidden gem": 205,
  "honk": 233,
  "honksville": 111,
  "hoptimistic": 4614,
  "how to breathe": 811,
  "how to get rich the quickest": 1017,
  "how to talk to your mods about responsible wheel spins": 4004,
  "id-10t error": 95,
  "iron": 365,
  "iron works": 44,
  "is this the tower?": 446,
  "item locations": 801,
  "item mastery song": 2699,
  "items": 410,
  "jackie": 138,
  "jello": 600,
  "jello gang": 85,
  "jessica": 154,
  "jokes": 2511,
  "leafmealone": 142,
  "leafmeolone": 187,
  "level xp": 548,
  "librarians": 710,
  "lima bean empire": 1338,
  "links": 1340,
  "llek spin": 45,
  "lock smith": 1436,
  "magicandwires": 175,
  "magpie cat": 1309,
  "mailbox upgrades": 1065,
  "manual fish": 3589,
  "mb pw": 682,
  "mbpw": 3925,
  "monke": 82,
  "mushroom gang": 478,
  "nails": 89,
  "name": 1230,
  "nice library page": 1799,
  "nicer library page": 3073,
  "nicolas cage": 105,
  "nomination giveaway": 5654,
  "noot": 3767,
  "not stonks": 4450,
  "null": 112,
  "oh you": 383,
  "one billion": 313,
  "onion": 454,
  "optimism": 152,
  "otter romp": 403,
  "panda gang": 189,
  "pandas": 1175,
  "peach": 1013,
  "peach gang": 908,
  "pear": 916,
  "pebcak error": 69,
  "pebkac error": 66,
  "penguin gang": 1037,
  "perk list": 635,
  "pet": 2694,
  "pet tier list by auggie": 23821,
  "petshop": 328,
  "pig gang": 1140,
  "please chill": 528,
  "pog": 155,
  "pony gang": 915,
  "puffer gang": 1773,
  "pw": 205,
  "rapture pen": 3003,
  "read the quest song": 7251,
  "referral code": 347,
  "reset checklist": 7866,
  "rtq": 1277,
  "runestone": 7348,
  "ryber": 132,
  "salt": 1407,
  "salty": 2358,
  "saph": 292,
  "says": 528,
  "se": 1712,
  "sealworms": 966,
  "sell it": 939,
  "server lag": 259,
  "sga": 206,
  "silver fairies": 440,
  "skull gang": 942,
  "snackpath": 5168,
  "snowball": 872,
  "snowball fight": 1088,
  "soon": 19,
  "soontm": 916,
  "spoilers": 128821,
  "spoliers": 166,
  "starter emblem gang": 1913,
  "steak market": 4501,
  "stonks": 5710,
  "storehouse storage": 4738,
  "strange onion club": 1219,
  "strange ring gang": 1235,
  "strawberry gang": 198,
  "super  rares": 4005,
  "super rare": 2025,
  "super rares": 48133,
  "super rates": 768,
  "support ticket": 137,
  "tea kettle gang": 779,
  "templeofstones": 50,
  "the plane": 131,
  "the tower spoiler": 3453,
  "the vault": 7104,
  "the wheel": 1028,
  "tower construction": 4024,
  "tower entry": 469,
  "tower keys": 4249,
  "town hall": 379,
  "trapped": 2118,
  "tree gang": 799,
  "tribal mask gang": 1844,
  "trust the quest": 4390,
  "unlocks": 6321,
  "unpolished jade": 794,
  "upj": 84,
  "valentines event": 197,
  "wade": 119,
  "we want": 159,
  "we wants": 722,
  "what are we doing": 560,
  "wheel of Borgen": 3946,
  "wob": 97,
  "wood": 223,
  "world stats": 1155,
  "wuarry": 351,
  "ww drops table": 10382,
  "ww want": 1838,
  "ww wants": 46003,
  "www": 2522,
  "www.farmrpg.com": 110,
  "yddub": 293,
  "your mother": 559
}