{
  "1": 0,
  "2": 0,
  "3": 1,
  "4": 0,
  "5": 1,
  "6": 0,
  "7": 2,
  "8": 2,
  "9": 3,
  "10": 14,
  "11": 7,
  "12": 7,
  "13": 8,
  "14": 11,
  "15": 19,
  "16": 17,
  "17": 26,
  "18": 21,
  "19": 8,
  "20": 89,
  "21": 24,
  "22": 33,
  "23": 25,
  "24": 38,
  "25": 29,
  "26": 24,
  "27": 35,
  "28": 39,
  "29": 15,
  "30": 117,
  "31": 50,
  "32": 51,
  "33": 51,
  "34": 60,
  "35": 67,
  "36": 47,
  "37": 58,
  "38": 47,
  "39": 30,
  "40": 122,
  "41": 57,
  "42": 47,
  "43": 44,
  "44": 46,
  "45": 50,
  "46": 48,
  "47": 44,
  "48": 35,
  "49": 30,
  "50": 128,
  "51": 47,
  "52": 45,
  "53": 37,
  "54": 47,
  "55": 41,
  "56": 39,
  "57": 30,
  "58": 34,
  "59": 25,
  "60": 82,
  "61": 45,
  "62": 41,
  "63": 53,
  "64": 36,
  "65": 42,
  "66": 39,
  "67": 28,
  "68": 32,
  "69": 15,
  "70": 84,
  "71": 38,
  "72": 24,
  "73": 25,
  "74": 32,
  "75": 23,
  "76": 22,
  "77": 24,
  "78": 15,
  "79": 9,
  "80": 60,
  "81": 14,
  "82": 20,
  "83": 19,
  "84": 22,
  "85": 29,
  "86": 16,
  "87": 12,
  "88": 11,
  "89": 12,
  "90": 36,
  "91": 8,
  "92": 17,
  "93": 4,
  "94": 14,
  "95": 13,
  "96": 5,
  "97": 7,
  "98": 10,
  "99": 5,
  "100": 79,
  "101": 27,
  "102": 23,
  "103": 23,
  "104": 18,
  "105": 28,
  "106": 32,
  "107": 19,
  "108": 21,
  "109": 10,
  "110": 143,
  "111": 28,
  "112": 19,
  "113": 15,
  "114": 17,
  "115": 10,
  "116": 6,
  "117": 5,
  "118": 4,
  "119": 82
}