{
  "1": 3,
  "2": 0,
  "3": 1,
  "4": 2,
  "5": 2,
  "6": 3,
  "7": 2,
  "8": 0,
  "9": 5,
  "10": 11,
  "11": 6,
  "12": 13,
  "13": 6,
  "14": 13,
  "15": 11,
  "16": 18,
  "17": 17,
  "18": 15,
  "19": 15,
  "20": 89,
  "21": 28,
  "22": 25,
  "23": 30,
  "24": 38,
  "25": 36,
  "26": 21,
  "27": 20,
  "28": 37,
  "29": 20,
  "30": 126,
  "31": 48,
  "32": 44,
  "33": 58,
  "34": 52,
  "35": 51,
  "36": 39,
  "37": 51,
  "38": 36,
  "39": 30,
  "40": 129,
  "41": 54,
  "42": 54,
  "43": 52,
  "44": 62,
  "45": 54,
  "46": 46,
  "47": 49,
  "48": 51,
  "49": 44,
  "50": 119,
  "51": 80,
  "52": 44,
  "53": 52,
  "54": 66,
  "55": 53,
  "56": 59,
  "57": 34,
  "58": 47,
  "59": 27,
  "60": 119,
  "61": 82,
  "62": 65,
  "63": 55,
  "64": 58,
  "65": 51,
  "66": 55,
  "67": 51,
  "68": 35,
  "69": 37,
  "70": 101,
  "71": 39,
  "72": 30,
  "73": 39,
  "74": 33,
  "75": 36,
  "76": 41,
  "77": 33,
  "78": 32,
  "79": 20,
  "80": 77,
  "81": 42,
  "82": 37,
  "83": 30,
  "84": 29,
  "85": 34,
  "86": 23,
  "87": 35,
  "88": 19,
  "89": 11,
  "90": 59,
  "91": 28,
  "92": 18,
  "93": 23,
  "94": 20,
  "95": 20,
  "96": 15,
  "97": 10,
  "98": 12,
  "99": 4,
  "100": 91,
  "101": 35,
  "102": 27,
  "103": 25,
  "104": 24,
  "105": 16,
  "106": 22,
  "107": 18,
  "108": 20,
  "109": 12,
  "110": 151,
  "111": 26,
  "112": 24,
  "113": 21,
  "114": 24,
  "115": 21,
  "116": 21,
  "117": 15,
  "118": 16,
  "119": 19,
  "120": 70,
  "121": 19,
  "122": 14,
  "123": 13,
  "124": 19,
  "125": 22,
  "126": 12,
  "127": 17,
  "128": 12,
  "129": 14,
  "130": 37,
  "131": 10,
  "132": 11,
  "133": 14,
  "134": 8,
  "135": 6,
  "136": 9,
  "137": 14,
  "138": 8,
  "139": 9,
  "140": 31,
  "141": 16,
  "142": 15,
  "143": 6,
  "144": 8,
  "145": 11,
  "146": 16,
  "147": 18,
  "148": 3,
  "149": 436
}