{
  "1": 1,
  "2": 0,
  "3": 2,
  "4": 1,
  "5": 4,
  "6": 3,
  "7": 4,
  "8": 4,
  "9": 7,
  "10": 14,
  "11": 10,
  "12": 14,
  "13": 8,
  "14": 14,
  "15": 12,
  "16": 8,
  "17": 23,
  "18": 11,
  "19": 18,
  "20": 98,
  "21": 33,
  "22": 24,
  "23": 29,
  "24": 34,
  "25": 37,
  "26": 26,
  "27": 28,
  "28": 33,
  "29": 17,
  "30": 115,
  "31": 52,
  "32": 39,
  "33": 66,
  "34": 55,
  "35": 53,
  "36": 64,
  "37": 53,
  "38": 46,
  "39": 45,
  "40": 169,
  "41": 59,
  "42": 56,
  "43": 54,
  "44": 49,
  "45": 65,
  "46": 56,
  "47": 52,
  "48": 43,
  "49": 36,
  "50": 136,
  "51": 76,
  "52": 62,
  "53": 61,
  "54": 61,
  "55": 71,
  "56": 69,
  "57": 47,
  "58": 54,
  "59": 28,
  "60": 120,
  "61": 67,
  "62": 54,
  "63": 55,
  "64": 61,
  "65": 57,
  "66": 56,
  "67": 49,
  "68": 39,
  "69": 30,
  "70": 97,
  "71": 52,
  "72": 41,
  "73": 42,
  "74": 39,
  "75": 54,
  "76": 43,
  "77": 40,
  "78": 29,
  "79": 20,
  "80": 87,
  "81": 37,
  "82": 33,
  "83": 38,
  "84": 32,
  "85": 48,
  "86": 23,
  "87": 25,
  "88": 25,
  "89": 12,
  "90": 61,
  "91": 24,
  "92": 25,
  "93": 21,
  "94": 21,
  "95": 19,
  "96": 21,
  "97": 16,
  "98": 16,
  "99": 7,
  "100": 101,
  "101": 53,
  "102": 31,
  "103": 32,
  "104": 23,
  "105": 30,
  "106": 31,
  "107": 20,
  "108": 15,
  "109": 11,
  "110": 144,
  "111": 34,
  "112": 17,
  "113": 24,
  "114": 25,
  "115": 18,
  "116": 30,
  "117": 21,
  "118": 30,
  "119": 19,
  "120": 110,
  "121": 28,
  "122": 13,
  "123": 27,
  "124": 24,
  "125": 25,
  "126": 18,
  "127": 13,
  "128": 19,
  "129": 13,
  "130": 143,
  "131": 20,
  "132": 13,
  "133": 10,
  "134": 14,
  "135": 16,
  "136": 12,
  "137": 22,
  "138": 8,
  "139": 19,
  "140": 48,
  "141": 23,
  "142": 14,
  "143": 19,
  "144": 12,
  "145": 11,
  "146": 13,
  "147": 14,
  "148": 5,
  "149": 1475
}