{
  "1": 2,
  "2": 0,
  "3": 1,
  "4": 1,
  "5": 3,
  "6": 1,
  "7": 5,
  "8": 2,
  "9": 5,
  "10": 15,
  "11": 5,
  "12": 10,
  "13": 10,
  "14": 13,
  "15": 17,
  "16": 10,
  "17": 17,
  "18": 20,
  "19": 13,
  "20": 115,
  "21": 31,
  "22": 20,
  "23": 27,
  "24": 32,
  "25": 34,
  "26": 19,
  "27": 33,
  "28": 30,
  "29": 19,
  "30": 103,
  "31": 50,
  "32": 47,
  "33": 63,
  "34": 56,
  "35": 60,
  "36": 53,
  "37": 55,
  "38": 50,
  "39": 42,
  "40": 153,
  "41": 66,
  "42": 54,
  "43": 53,
  "44": 57,
  "45": 59,
  "46": 62,
  "47": 54,
  "48": 34,
  "49": 37,
  "50": 131,
  "51": 83,
  "52": 59,
  "53": 48,
  "54": 58,
  "55": 74,
  "56": 55,
  "57": 46,
  "58": 57,
  "59": 25,
  "60": 122,
  "61": 80,
  "62": 58,
  "63": 48,
  "64": 62,
  "65": 54,
  "66": 59,
  "67": 53,
  "68": 50,
  "69": 30,
  "70": 115,
  "71": 47,
  "72": 31,
  "73": 45,
  "74": 40,
  "75": 38,
  "76": 41,
  "77": 36,
  "78": 24,
  "79": 16,
  "80": 93,
  "81": 49,
  "82": 41,
  "83": 36,
  "84": 31,
  "85": 43,
  "86": 20,
  "87": 21,
  "88": 26,
  "89": 16,
  "90": 57,
  "91": 28,
  "92": 21,
  "93": 32,
  "94": 18,
  "95": 17,
  "96": 22,
  "97": 12,
  "98": 6,
  "99": 9,
  "100": 91,
  "101": 45,
  "102": 30,
  "103": 37,
  "104": 27,
  "105": 38,
  "106": 29,
  "107": 26,
  "108": 15,
  "109": 12,
  "110": 153,
  "111": 39,
  "112": 28,
  "113": 34,
  "114": 26,
  "115": 30,
  "116": 25,
  "117": 33,
  "118": 26,
  "119": 21,
  "120": 96,
  "121": 25,
  "122": 26,
  "123": 25,
  "124": 17,
  "125": 11,
  "126": 21,
  "127": 19,
  "128": 11,
  "129": 17,
  "130": 85,
  "131": 14,
  "132": 13,
  "133": 17,
  "134": 19,
  "135": 12,
  "136": 14,
  "137": 15,
  "138": 15,
  "139": 18,
  "140": 34,
  "141": 12,
  "142": 10,
  "143": 10,
  "144": 11,
  "145": 14,
  "146": 17,
  "147": 13,
  "148": 4,
  "149": 1227
}